LICENSE
README.md
setup.py
vscode/__init__.py
vscode/compiler.py
vscode/config.py
vscode/context.py
vscode/enums.py
vscode/env.py
vscode/extcode.py
vscode/extension.py
vscode/objects.py
vscode/utils.py
vscode/webviews.py
vscode/window.py
vscode/workspace.py
vscode/wsclient.py
vscode.py.egg-info/PKG-INFO
vscode.py.egg-info/SOURCES.txt
vscode.py.egg-info/dependency_links.txt
vscode.py.egg-info/requires.txt
vscode.py.egg-info/top_level.txt