Metadata-Version: 2.1
Name: vscode.py
Version: 2.0.0b1
Summary: Create VSCode Extensions with python
Home-page: https://github.com/CodeWithSwastik/vscode-ext
Author: Swas.py
Author-email: cwswas.py@gmail.com
Project-URL: Issue tracker, https://github.com/CodeWithSwastik/vscode-ext/issues
Classifier: Programming Language :: Python :: 3
Classifier: Development Status :: 4 - Beta
Classifier: Intended Audience :: Developers
Classifier: License :: OSI Approved :: MIT License
Classifier: Operating System :: OS Independent
Classifier: Topic :: Internet
Classifier: Topic :: Software Development :: Libraries
Classifier: Topic :: Software Development :: Libraries :: Python Modules
Classifier: Topic :: Utilities
Requires-Python: >=3.8
License-File: LICENSE
